setup.py
Tools/__init__.py
Tools/Common/Font.py
Tools/Common/Input.py
Tools/Common/Output.py
Tools/Common/__init__.py
Tools/Files/PDFFile.py
Tools/Files/WordFile.py
Tools/Files/__init__.py
Tools/Math/Arrange.py
Tools/Math/Combination.py
Tools/Math/Constants.py
Tools/Math/Math.py
Tools/Math/Statistics.py
Tools/Math/__init__.py
Useful_Tools.egg-info/PKG-INFO
Useful_Tools.egg-info/SOURCES.txt
Useful_Tools.egg-info/dependency_links.txt
Useful_Tools.egg-info/requires.txt
Useful_Tools.egg-info/top_level.txt