Metadata-Version: 1.0
Name: Useful-Tools
Version: 0.0.3
Summary: Some useful tools.
Home-page: https://github.com/zhangletao/Tools
Author: zltzlt
Author-email: 1668151593@qq.com
License: UNKNOWN
Platform: UNKNOWN
